hent/__init__.py
hent/__main__.py
hent/console_script.py
hent-1.0.5.dist-info/LICENSE
hent-1.0.5.dist-info/METADATA
hent-1.0.5.dist-info/WHEEL
hent-1.0.5.dist-info/entry_points.txt
hent-1.0.5.dist-info/top_level.txt
hent-1.0.5.dist-info/RECORD
