Metadata-Version: 2.1
Name: hent
Version: 1.0.5
Summary: A neofetch alternative written in python.
Home-page: https://github.com/imsofi/hent
Author: Sofi
Author-email: sofi+hent@mailbox.org
License: MIT
Classifier: Development Status :: 3 - Alpha
Classifier: Environment :: Console
Classifier: License :: OSI Approved :: MIT License
Classifier: Operating System :: POSIX :: Linux
Classifier: Programming Language :: Python :: 3
Requires-Python: >=3.6
License-File: LICENSE
Requires-Dist: psutil
